{"cameraMode":{"drawMode":0,"name":"Shaded","section":"Shading Mode"},"sceneLighting":true,"audioPlay":false,"sceneViewState":{"showFog":true,"showMaterialUpdate":false,"showSkybox":true,"showFlares":true,"showImageEffects":true,"showParticleSystems":true},"in2DMode":false,"pivot":{"x":0.023651957511901857,"y":-0.1309274435043335,"z":0.2315322756767273},"rotation":{"x":0.18695534765720368,"y":-0.16808649897575379,"z":0.03221222758293152,"w":0.9676601886749268},"size":2.445213794708252,"orthographic":false}